aiounifi/__init__.py
aiounifi/__main__.py
aiounifi/controller.py
aiounifi/errors.py
aiounifi/py.typed
aiounifi/interfaces/__init__.py
aiounifi/interfaces/api_handlers.py
aiounifi/interfaces/clients.py
aiounifi/interfaces/clients_all.py
aiounifi/interfaces/connectivity.py
aiounifi/interfaces/devices.py
aiounifi/interfaces/dpi_restriction_apps.py
aiounifi/interfaces/dpi_restriction_groups.py
aiounifi/interfaces/events.py
aiounifi/interfaces/firewall_policies.py
aiounifi/interfaces/firewall_zones.py
aiounifi/interfaces/messages.py
aiounifi/interfaces/outlets.py
aiounifi/interfaces/port_forwarding.py
aiounifi/interfaces/ports.py
aiounifi/interfaces/sites.py
aiounifi/interfaces/system_information.py
aiounifi/interfaces/traffic_routes.py
aiounifi/interfaces/traffic_rules.py
aiounifi/interfaces/vouchers.py
aiounifi/interfaces/wlans.py
aiounifi/models/__init__.py
aiounifi/models/api.py
aiounifi/models/client.py
aiounifi/models/configuration.py
aiounifi/models/device.py
aiounifi/models/dpi_restriction_app.py
aiounifi/models/dpi_restriction_group.py
aiounifi/models/event.py
aiounifi/models/firewall_policy.py
aiounifi/models/firewall_zone.py
aiounifi/models/message.py
aiounifi/models/outlet.py
aiounifi/models/port.py
aiounifi/models/port_forward.py
aiounifi/models/site.py
aiounifi/models/system_information.py
aiounifi/models/traffic_route.py
aiounifi/models/traffic_rule.py
aiounifi/models/voucher.py
aiounifi/models/wlan.py
aiounifi-88.dist-info/licenses/LICENSE
aiounifi-88.dist-info/METADATA
aiounifi-88.dist-info/WHEEL
aiounifi-88.dist-info/entry_points.txt
aiounifi-88.dist-info/top_level.txt
aiounifi-88.dist-info/RECORD
