Metadata-Version: 2.4
Name: aiounifi
Version: 88
Summary: Python library for communicating with UniFi Network Controller API
Author-email: Robert Svensson <Kane610@users.noreply.github.com>
License: MIT
Project-URL: Source Code, https://github.com/Kane610/aiounifi
Project-URL: Bug Reports, https://github.com/Kane610/aiounifi/issues
Project-URL: Forum, https://community.home-assistant.io/t/unifi-network-integration-official-thread/
Keywords: unifi,homeassistant
Classifier: Development Status :: 5 - Production/Stable
Classifier: Intended Audience :: Developers
Classifier: License :: OSI Approved :: MIT License
Classifier: Operating System :: OS Independent
Classifier: Programming Language :: Python :: 3.13
Classifier: Topic :: Home Automation
Requires-Python: >=3.13.0
License-File: LICENSE
Requires-Dist: aiohttp>3.9
Requires-Dist: orjson>3.9
Requires-Dist: segno>=1.5.2
Provides-Extra: requirements
Requires-Dist: aiohttp==3.13.2; extra == "requirements"
Requires-Dist: orjson==3.11.4; extra == "requirements"
Requires-Dist: segno==1.6.6; extra == "requirements"
Provides-Extra: requirements-test
Requires-Dist: aioresponses==0.7.8; extra == "requirements-test"
Requires-Dist: mypy==1.18.2; extra == "requirements-test"
Requires-Dist: pytest==9.0.0; extra == "requirements-test"
Requires-Dist: pytest-aiohttp==1.1.0; extra == "requirements-test"
Requires-Dist: pytest-asyncio==1.3.0; extra == "requirements-test"
Requires-Dist: pytest-cov==7.0.0; extra == "requirements-test"
Requires-Dist: ruff==0.14.4; extra == "requirements-test"
Requires-Dist: trustme==1.2.1; extra == "requirements-test"
Requires-Dist: types-orjson==3.6.2; extra == "requirements-test"
Provides-Extra: requirements-dev
Requires-Dist: pre-commit==4.4.0; extra == "requirements-dev"
Dynamic: license-file
